zapusk/__init__.py
zapusk/__main__.py
zapusk/client/__init__.py
zapusk/client/__main__.py
zapusk/client/api_client.py
zapusk/client/api_client_test.py
zapusk/client/command.py
zapusk/client/command_cancel.py
zapusk/client/command_cancel_test.py
zapusk/client/command_config_groups.py
zapusk/client/command_config_groups_test.py
zapusk/client/command_config_jobs.py
zapusk/client/command_config_jobs_test.py
zapusk/client/command_exec.py
zapusk/client/command_exec_test.py
zapusk/client/command_list.py
zapusk/client/command_list_test.py
zapusk/client/command_manager.py
zapusk/client/command_run.py
zapusk/client/command_run_test.py
zapusk/client/command_tail.py
zapusk/client/command_tail_test.py
zapusk/client/command_testcase.py
zapusk/client/command_waybar.py
zapusk/client/command_waybar_test.py
zapusk/client/output.py
zapusk/client/output_test.py
zapusk/client/printer.py
zapusk/client/printer_test.py
zapusk/kawka/__init__.py
zapusk/kawka/consumer.py
zapusk/kawka/consumer_group.py
zapusk/kawka/consumer_group_test.py
zapusk/kawka/consumer_test.py
zapusk/kawka/linked_list.py
zapusk/kawka/linked_list_test.py
zapusk/kawka/producer.py
zapusk/kawka/producer_test.py
zapusk/kawka/topic.py
zapusk/kawka/topic_iterator.py
zapusk/kawka/topic_test.py
zapusk/lib/__init__.py
zapusk/lib/create_jobitem.py
zapusk/lib/json_serdes.py
zapusk/lib/json_serdes_test.py
zapusk/logger.py
zapusk/models/__init__.py
zapusk/models/base_model.py
zapusk/models/base_model_test.py
zapusk/models/config.py
zapusk/models/id_field.py
zapusk/models/id_field_test.py
zapusk/models/job.py
zapusk/models/job_config.py
zapusk/models/job_group.py
zapusk/models/scheduled_job.py
zapusk/server/__init__.py
zapusk/server/api.py
zapusk/server/controller_config.py
zapusk/server/controller_config_test.py
zapusk/server/controller_jobs.py
zapusk/server/controller_jobs_test.py
zapusk/server/controller_scheduled_jobs.py
zapusk/server/controller_scheduled_jobs_test.py
zapusk/server/controller_testcase.py
zapusk-0.1.1.dist-info/LICENSE.md
zapusk-0.1.1.dist-info/METADATA
zapusk-0.1.1.dist-info/WHEEL
zapusk-0.1.1.dist-info/entry_points.txt
zapusk-0.1.1.dist-info/RECORD
