Metadata-Version: 2.1
Name: zapusk
Version: 0.1.1
Summary: 
Author: Anton Shuvalov
Author-email: anton@shuvalov.info
Requires-Python: >=3.12,<4.0
Classifier: Programming Language :: Python :: 3
Classifier: Programming Language :: Python :: 3.12
Requires-Dist: croniter (>=2.0.5,<3.0.0)
Requires-Dist: docopt (>=0.6.2,<0.7.0)
Requires-Dist: flask (>=3.0.3,<4.0.0)
Requires-Dist: human-readable (>=1.3.4,<2.0.0)
Requires-Dist: pdoc (>=14.5.1,<15.0.0)
Requires-Dist: pygments (>=2.18.0,<3.0.0)
Requires-Dist: python-dateutil (>=2.9.0.post0,<3.0.0)
Requires-Dist: pyyaml (>=6.0.1,<7.0.0)
Requires-Dist: requests (>=2.32.3,<3.0.0)
Requires-Dist: sh (>=2.0.7,<3.0.0)
Requires-Dist: type-docopt (>=0.8.2,<0.9.0)
